{
  "pluginId": "default",
  "version": "current",
  "label": "Next",
  "banner": null,
  "badge": false,
  "noIndex": false,
  "className": "docs-version-current",
  "isLast": true,
  "docsSidebars": {
    "tutorialSidebar": [
      {
        "type": "link",
        "label": "Documentation",
        "href": "/",
        "docId": "index",
        "unlisted": false
      },
      {
        "type": "category",
        "label": "Human",
        "collapsible": true,
        "collapsed": true,
        "items": [
          {
            "type": "category",
            "label": "Human SpikerBox",
            "collapsible": true,
            "collapsed": true,
            "items": [
              {
                "type": "link",
                "label": "Reaction Timer",
                "href": "/Human/HumanSB/ReactionTimer/",
                "docId": "Human/HumanSB/ReactionTimer/index",
                "unlisted": false
              },
              {
                "type": "link",
                "label": "Reflex Hammer",
                "href": "/Human/HumanSB/ReflexHammer/",
                "docId": "Human/HumanSB/ReflexHammer/index",
                "unlisted": false
              },
              {
                "type": "link",
                "label": "Game Controller",
                "href": "/Human/HumanSB/GameController/",
                "docId": "Human/HumanSB/GameController/index",
                "unlisted": false
              }
            ],
            "href": "/Human/HumanSB/"
          },
          {
            "type": "link",
            "label": "Human-Human Interface",
            "href": "/Human/HHI/",
            "docId": "Human/HHI/index",
            "unlisted": false
          },
          {
            "type": "link",
            "label": "The Claw",
            "href": "/Human/Claw/",
            "docId": "Human/Claw/index",
            "unlisted": false
          },
          {
            "type": "link",
            "label": "Heart and Brain SpikerBox",
            "href": "/Human/H&BSB/",
            "docId": "Human/H&BSB/index",
            "unlisted": false
          },
          {
            "type": "category",
            "label": "Muscle SpikerShield",
            "collapsible": true,
            "collapsed": true,
            "items": [
              {
                "type": "link",
                "label": "DIY Neuroprosthetic Kit",
                "href": "/Human/MuscleSS/DIYNP/",
                "docId": "Human/MuscleSS/DIYNP/index",
                "unlisted": false
              }
            ],
            "href": "/Human/MuscleSS/"
          },
          {
            "type": "link",
            "label": "Muscle SpikerBox",
            "href": "/Human/MuscleSB/",
            "docId": "Human/MuscleSB/index",
            "unlisted": false
          }
        ],
        "href": "/Human/"
      },
      {
        "type": "category",
        "label": "Insect",
        "collapsible": true,
        "collapsed": true,
        "items": [
          {
            "type": "link",
            "label": "Neuron SpikerBox Classic",
            "href": "/Insect/NSBclassic/",
            "docId": "Insect/NSBclassic/index",
            "unlisted": false
          },
          {
            "type": "link",
            "label": "Neuron SpikerBox Pro",
            "href": "/Insect/NSBpro/",
            "docId": "Insect/NSBpro/index",
            "unlisted": false
          },
          {
            "type": "link",
            "label": "RoboRoach",
            "href": "/Insect/Roboroach/",
            "docId": "Insect/Roboroach/index",
            "unlisted": false
          }
        ],
        "href": "/Insect/"
      },
      {
        "type": "category",
        "label": "Plant",
        "collapsible": true,
        "collapsed": true,
        "items": [
          {
            "type": "link",
            "label": "Plant SpikerBox",
            "href": "/Plant/PlantSpikerBox/",
            "docId": "Plant/PlantSpikerBox/index",
            "unlisted": false
          }
        ],
        "href": "/Plant/"
      },
      {
        "type": "category",
        "label": "Policies",
        "collapsible": true,
        "collapsed": true,
        "items": [
          {
            "type": "link",
            "label": "index",
            "href": "/Policies/Ethics/",
            "docId": "Policies/Ethics/index",
            "unlisted": false
          },
          {
            "type": "link",
            "label": "index",
            "href": "/Policies/ReturnPolicy/",
            "docId": "Policies/ReturnPolicy/index",
            "unlisted": false
          },
          {
            "type": "link",
            "label": "index",
            "href": "/Policies/StyleGuide/",
            "docId": "Policies/StyleGuide/index",
            "unlisted": false
          }
        ]
      },
      {
        "type": "category",
        "label": "Software",
        "collapsible": true,
        "collapsed": true,
        "items": [
          {
            "type": "category",
            "label": "Spike Recorder",
            "collapsible": true,
            "collapsed": true,
            "items": [
              {
                "type": "link",
                "label": "Windows/Mac/Linux",
                "href": "/Software/SpikeRecorder/Desktop/",
                "docId": "Software/SpikeRecorder/Desktop/index",
                "unlisted": false
              },
              {
                "type": "link",
                "label": "iOS",
                "href": "/Software/SpikeRecorder/iOS/",
                "docId": "Software/SpikeRecorder/iOS/index",
                "unlisted": false
              },
              {
                "type": "link",
                "label": "Android",
                "href": "/Software/SpikeRecorder/Android/",
                "docId": "Software/SpikeRecorder/Android/index",
                "unlisted": false
              },
              {
                "type": "link",
                "label": "Web (in development)",
                "href": "/Software/SpikeRecorder/Web/",
                "docId": "Software/SpikeRecorder/Web/index",
                "unlisted": false
              },
              {
                "type": "link",
                "label": "Troubleshooting",
                "href": "/Software/SpikeRecorder/Troubleshooting/",
                "docId": "Software/SpikeRecorder/Troubleshooting/index",
                "unlisted": false
              }
            ],
            "href": "/Software/SpikeRecorder/"
          }
        ]
      }
    ]
  },
  "docs": {
    "Human/Claw/index": {
      "id": "Human/Claw/index",
      "title": "The Claw",
      "description": "image of claw",
      "sidebar": "tutorialSidebar"
    },
    "Human/H&BSB/index": {
      "id": "Human/H&BSB/index",
      "title": "The Heart and Brain SpikerBox",
      "description": "image",
      "sidebar": "tutorialSidebar"
    },
    "Human/HHI/index": {
      "id": "Human/HHI/index",
      "title": "Human-Human Interface",
      "description": "image",
      "sidebar": "tutorialSidebar"
    },
    "Human/HumanSB/GameController/index": {
      "id": "Human/HumanSB/GameController/index",
      "title": "Game Controller",
      "description": "Please Note: Works on Windows only and requires a Human SpikerBox",
      "sidebar": "tutorialSidebar"
    },
    "Human/HumanSB/index": {
      "id": "Human/HumanSB/index",
      "title": "Human SpikerBox",
      "description": "One box to rule them all! Reveal and record the electrical activity hidden within your muscles, heart, brain, eyes and more! This easy-to-use kit allows you to record EMG, EKG, EEG, and EOG signals, giving you the power to perform human physiology experiments!",
      "sidebar": "tutorialSidebar"
    },
    "Human/HumanSB/ReactionTimer/index": {
      "id": "Human/HumanSB/ReactionTimer/index",
      "title": "Reaction Timer",
      "description": "Please Note: Requires a Human SpikerBox and a USB connection to an Android device, Mac, PC Desktop or iPhone/iPad with USB-C connector. Not compatible with iPhones or iPads with lightning connectors",
      "sidebar": "tutorialSidebar"
    },
    "Human/HumanSB/ReflexHammer/index": {
      "id": "Human/HumanSB/ReflexHammer/index",
      "title": "Reflex Hammer",
      "description": "Please Note: Requires a Human SpikerBox and a USB connection to an Android device, Mac, PC Desktop or iPhone/iPad with USB-C connector. Not compatible with iPhones or iPads with lightning connectors",
      "sidebar": "tutorialSidebar"
    },
    "Human/index": {
      "id": "Human/index",
      "title": "Human",
      "description": "",
      "sidebar": "tutorialSidebar"
    },
    "Human/MuscleSB/index": {
      "id": "Human/MuscleSB/index",
      "title": "Muscle SpikerBox",
      "description": "image",
      "sidebar": "tutorialSidebar"
    },
    "Human/MuscleSS/DIYNP/index": {
      "id": "Human/MuscleSS/DIYNP/index",
      "title": "DIY Neuroprosthetic Kit",
      "description": "NOT A STANDALONE PRODUCT, Requires Muscle SpikerShield",
      "sidebar": "tutorialSidebar"
    },
    "Human/MuscleSS/index": {
      "id": "Human/MuscleSS/index",
      "title": "Muscle SpikerShield",
      "description": "image",
      "sidebar": "tutorialSidebar"
    },
    "index": {
      "id": "index",
      "title": "Documentation",
      "description": "Welcome to Backyard Brains' Documentation ##",
      "sidebar": "tutorialSidebar"
    },
    "Insect/index": {
      "id": "Insect/index",
      "title": "Insect",
      "description": "",
      "sidebar": "tutorialSidebar"
    },
    "Insect/NSBclassic/index": {
      "id": "Insect/NSBclassic/index",
      "title": "Neuron SpikerBox Classic",
      "description": "nsb classic",
      "sidebar": "tutorialSidebar"
    },
    "Insect/NSBpro/index": {
      "id": "Insect/NSBpro/index",
      "title": "Neuron SpikerBox Pro",
      "description": "nsb pro",
      "sidebar": "tutorialSidebar"
    },
    "Insect/Roboroach/index": {
      "id": "Insect/Roboroach/index",
      "title": "The RoboRoach",
      "description": "Please Note: Requires at least one Cockroach",
      "sidebar": "tutorialSidebar"
    },
    "Plant/index": {
      "id": "Plant/index",
      "title": "Plant",
      "description": "",
      "sidebar": "tutorialSidebar"
    },
    "Plant/PlantSpikerBox/index": {
      "id": "Plant/PlantSpikerBox/index",
      "title": "Plant SpikerBox",
      "description": "Psb",
      "sidebar": "tutorialSidebar"
    },
    "Policies/Ethics/index": {
      "id": "Policies/Ethics/index",
      "title": "index",
      "description": "",
      "sidebar": "tutorialSidebar"
    },
    "Policies/ReturnPolicy/index": {
      "id": "Policies/ReturnPolicy/index",
      "title": "index",
      "description": "",
      "sidebar": "tutorialSidebar"
    },
    "Policies/StyleGuide/index": {
      "id": "Policies/StyleGuide/index",
      "title": "index",
      "description": "",
      "sidebar": "tutorialSidebar"
    },
    "Software/SpikeRecorder/Android/index": {
      "id": "Software/SpikeRecorder/Android/index",
      "title": "Android",
      "description": "",
      "sidebar": "tutorialSidebar"
    },
    "Software/SpikeRecorder/Desktop/index": {
      "id": "Software/SpikeRecorder/Desktop/index",
      "title": "Windows/Mac/Linux",
      "description": "",
      "sidebar": "tutorialSidebar"
    },
    "Software/SpikeRecorder/index": {
      "id": "Software/SpikeRecorder/index",
      "title": "Spike Recorder",
      "description": "Our devices are ment to be used with our Spike Recorder Software available for Windows, macOS, iOS, Android and Linux",
      "sidebar": "tutorialSidebar"
    },
    "Software/SpikeRecorder/iOS/index": {
      "id": "Software/SpikeRecorder/iOS/index",
      "title": "iOS",
      "description": "",
      "sidebar": "tutorialSidebar"
    },
    "Software/SpikeRecorder/Troubleshooting/index": {
      "id": "Software/SpikeRecorder/Troubleshooting/index",
      "title": "Troubleshooting",
      "description": "",
      "sidebar": "tutorialSidebar"
    },
    "Software/SpikeRecorder/Web/index": {
      "id": "Software/SpikeRecorder/Web/index",
      "title": "Web (in development)",
      "description": "",
      "sidebar": "tutorialSidebar"
    }
  }
}